modulairy_mail_sender/__init__.py
modulairy_mail_sender-0.0.2.6.data/scripts/modulairy_mail_sender
modulairy_mail_sender-0.0.2.6.dist-info/LICENCE
modulairy_mail_sender-0.0.2.6.dist-info/METADATA
modulairy_mail_sender-0.0.2.6.dist-info/WHEEL
modulairy_mail_sender-0.0.2.6.dist-info/top_level.txt
modulairy_mail_sender-0.0.2.6.dist-info/RECORD
