Metadata-Version: 2.1
Name: modulairy-mail-sender
Version: 0.0.2.6
Summary: This script enables sending emails asynchronously from Azure Service Bus. Each bus message contains a sender's email address along with SMTP configurations. The script utilizes its SMTP configuration of the message for sending emails.
Home-page: https://github.com/modulairy/mail-sender
Author: Fatih Mehmet ARSLAN
Author-email: contact@fmarslan.com
Platform: all
Classifier: License :: OSI Approved :: Apache Software License
Classifier: Topic :: Internet
Classifier: Topic :: Software Development
Classifier: Topic :: Software Development :: Libraries
Classifier: Intended Audience :: Developers
Classifier: Operating System :: MacOS
Classifier: Operating System :: POSIX
Classifier: Operating System :: Microsoft
Classifier: Programming Language :: Python
Classifier: Programming Language :: Python :: 3.8
Requires-Python: >=3.8, <4
License-File: LICENCE
Requires-Dist: aiosmtplib
Requires-Dist: azure-servicebus
